templatebot/__init__.py
templatebot/bot.py
templatebot/cogs/__init__.py
templatebot/cogs/default.py
templatebot/utils/__init__.py
templatebot/utils/logger.py
templatebot-1.0.3.dist-info/LICENSE
templatebot-1.0.3.dist-info/METADATA
templatebot-1.0.3.dist-info/WHEEL
templatebot-1.0.3.dist-info/top_level.txt
templatebot-1.0.3.dist-info/RECORD
