Metadata-Version: 2.1
Name: templatebot
Version: 1.0.3
Summary: A template Discord bot
Home-page: https://github.com/vcokltfre/template-bot-v2
Author: vcokltfre
License: MIT
Platform: UNKNOWN
Requires-Python: >=3.6
Requires-Dist: discord.py
Requires-Dist: jishaku
Requires-Dist: termcolor
Requires-Dist: requests
Requires-Dist: aiohttp
